BEHAVIOURAL  MODEL/SEQUENTIAL CRTS/ASSIGNMENTS/assign1.v
//-------------------------------------------Tx Rx DESIGN CODE-------------------------------------------------

//FIFO 8 BIT
module fifo1 (
                input clk,rst,wr,rd,
                input [7:0]d_in,
                output reg[7:0]d_out
               );
    reg [7:0]mem [7:0]; //8 bit fifo memory
    reg[2:0]w_ptr,r_ptr; //3 bit write and read pointers

    always @(posedge clk or negedge rst)
    begin
        if(!rst) begin
            d_out<=0;
            {w_ptr,r_ptr}<=2'b00;
            end
        else begin 
            if(wr && !rd) begin
                mem[w_ptr]<=d_in;
                w_ptr<=w_ptr+1;
                end

            else
                if(!wr && rd) begin
                d_out<=mem[r_ptr];
                r_ptr<=r_ptr+1;
                end
            end
    end
endmodule

//PISO 8 BIT
module piso1(
                input clk,rst,mode,
                input [7:0]p_in,
                output reg s_out
             );
    reg[7:0]temp;

    always @(posedge clk or negedge rst)
    begin
        if(!rst)
            begin
                temp<=0;
                s_out<=0;
            end
        else
            begin
                if(mode)
                    temp<=p_in;
                else
                    begin
                        s_out<=temp[0];
                        temp<=temp>>1;
                    end
            end
    end
endmodule

//SIPO 8 BIT
    module sipo1(
                    input clk,rst,s_in,mode,
                    output reg[7:0]p_out
                );
    reg [7:0]temp;

    always @(posedge clk or negedge rst)
    begin
        if(!rst)
            begin
                temp<=0;
                p_out<=0;
            end
        else 
            begin
                if(!mode)
                    begin
                        temp<={s_in,temp[7:1]};
                    end
                else
                    p_out<=temp;
            end
    end
    endmodule
 //------------------------------------------------------------Tx-Rx ALL INSTANTIATION Design Code---------------------------------------------------------
 module txrx1(
                input clk,rst,wr1,rd1,wr2,rd2,mode,
                input[7:0]data_in,
                output [7:0]data_out
             );
    wire[7:0]w1;
    wire w2;
    wire [7:0]w3;

    //instantiation
        fifo1 F1(.clk(clk),
                 .rst(rst),
                 .wr(wr1),
                 .rd(rd1),
                 .d_in(data_in),
                 .d_out(w1)
                );
        piso1 P1(
                .clk(clk),
                .rst(rst),
                .mode(mode),
                .p_in(w1),
                .s_out(w2)
                );
        sipo1 S1(
                  .clk(clk),
                  .rst(rst),
                  .mode(mode),
                  .s_in(w2),
                  .p_out(w3)
                );
        fifo1 F2(
                    .clk(clk),
                    .rst(rst),
                    .wr(wr2),
                    .rd(rd2),
                    .d_in(w3),
                    .d_out(data_out)
                );
 endmodule

BEHAVIOURAL  MODEL/SEQUENTIAL CRTS/ASSIGNMENTS/txrx_tb.v
`include "assign1.v"
//---------------------------------------------------TEST BENCH CODE----------------------
`timescale 1ns/1ps

module txrx_tb;
    reg clk, rst, wr1, rd1, wr2, rd2, mode;
    reg [7:0] data_in;
    wire [7:0] data_out;

    // Instantiate your design
    txrx1 DUT (
        .clk(clk),
        .rst(rst),
        .wr1(wr1),
        .rd1(rd1),
        .wr2(wr2),
        .rd2(rd2),
        .mode(mode),
        .data_in(data_in),
        .data_out(data_out)
    );

    // Clock generation: 10ns period
    always #5 clk = ~clk;

    initial begin
        $dumpfile("txrx_tb.vcd");
        $dumpvars(0, txrx_tb);

        // Initialize
        clk = 0; rst = 0;
        wr1 = 0; rd1 = 0; wr2 = 0; rd2 = 0;
        mode = 1; data_in = 0;

        // Reset system
        #10 rst = 1;

        // Continuous transmission loop
        forever begin
            // --- Send 18 ---
            #5 data_in = 8'd18; wr1 = 1; #10 wr1 = 0;
            rd1 = 1; #10 rd1 = 0;
            mode = 0; repeat(8) #10; mode = 1;
            wr2 = 1; #10 wr2 = 0;
            rd2 = 1; #10 rd2 = 0;
            $display("Output = %d", data_out);

            // --- Send 43 ---
            #25 data_in = 8'd43; wr1 = 1; #10 wr1 = 0;
            rd1 = 1; #10 rd1 = 0;
            mode = 0; repeat(8) #10; mode = 1;
            wr2 = 1; #10 wr2 = 0;
            rd2 = 1; #10 rd2 = 0;
            $display("Output = %d", data_out);

            // --- Send 64 ---
            #10 data_in = 8'd64; wr1 = 1; #10 wr1 = 0;
            rd1 = 1; #10 rd1 = 0;
            mode = 0; repeat(8) #10; mode = 1;
            wr2 = 1; #10 wr2 = 0;
            rd2 = 1; #10 rd2 = 0;
            $display("Output = %d", data_out);
        end
        
    end
    initial
#1000 $stop;
endmodule

BEHAVIOURAL  MODEL/SEQUENTIAL CRTS/ASSIGNMENTS/txrx_tb.vcd
$date
	Tue Nov 04 12:37:11 2025
$end
$version
	QuestaSim Version 10.7c
$end
$timescale
	1ps
$end

$scope module txrx_tb $end
$var reg 1 ! clk $end
$var reg 1 " rst $end
$var reg 1 # wr1 $end
$var reg 1 $ rd1 $end
$var reg 1 % wr2 $end
$var reg 1 & rd2 $end
$var reg 1 ' mode $end
$var reg 8 ( data_in [7:0] $end
$var wire 1 ) data_out [7] $end
$var wire 1 * data_out [6] $end
$var wire 1 + data_out [5] $end
$var wire 1 , data_out [4] $end
$var wire 1 - data_out [3] $end
$var wire 1 . data_out [2] $end
$var wire 1 / data_out [1] $end
$var wire 1 0 data_out [0] $end

$scope module DUT $end
$var wire 1 1 clk $end
$var wire 1 2 rst $end
$var wire 1 3 wr1 $end
$var wire 1 4 rd1 $end
$var wire 1 5 wr2 $end
$var wire 1 6 rd2 $end
$var wire 1 7 mode $end
$var wire 1 8 data_in [7] $end
$var wire 1 9 data_in [6] $end
$var wire 1 : data_in [5] $end
$var wire 1 ; data_in [4] $end
$var wire 1 < data_in [3] $end
$var wire 1 = data_in [2] $end
$var wire 1 > data_in [1] $end
$var wire 1 ? data_in [0] $end
$var wire 1 ) data_out [7] $end
$var wire 1 * data_out [6] $end
$var wire 1 + data_out [5] $end
$var wire 1 , data_out [4] $end
$var wire 1 - data_out [3] $end
$var wire 1 . data_out [2] $end
$var wire 1 / data_out [1] $end
$var wire 1 0 data_out [0] $end
$var wire 1 @ w1 [7] $end
$var wire 1 A w1 [6] $end
$var wire 1 B w1 [5] $end
$var wire 1 C w1 [4] $end
$var wire 1 D w1 [3] $end
$var wire 1 E w1 [2] $end
$var wire 1 F w1 [1] $end
$var wire 1 G w1 [0] $end
$var wire 1 H w2 $end
$var wire 1 I w3 [7] $end
$var wire 1 J w3 [6] $end
$var wire 1 K w3 [5] $end
$var wire 1 L w3 [4] $end
$var wire 1 M w3 [3] $end
$var wire 1 N w3 [2] $end
$var wire 1 O w3 [1] $end
$var wire 1 P w3 [0] $end

$scope module F1 $end
$var wire 1 1 clk $end
$var wire 1 2 rst $end
$var wire 1 3 wr $end
$var wire 1 4 rd $end
$var wire 1 8 d_in [7] $end
$var wire 1 9 d_in [6] $end
$var wire 1 : d_in [5] $end
$var wire 1 ; d_in [4] $end
$var wire 1 < d_in [3] $end
$var wire 1 = d_in [2] $end
$var wire 1 > d_in [1] $end
$var wire 1 ? d_in [0] $end
$var reg 8 Q d_out [7:0] $end
$var reg 3 R w_ptr [2:0] $end
$var reg 3 S r_ptr [2:0] $end
$upscope $end

$scope module P1 $end
$var wire 1 1 clk $end
$var wire 1 2 rst $end
$var wire 1 7 mode $end
$var wire 1 @ p_in [7] $end
$var wire 1 A p_in [6] $end
$var wire 1 B p_in [5] $end
$var wire 1 C p_in [4] $end
$var wire 1 D p_in [3] $end
$var wire 1 E p_in [2] $end
$var wire 1 F p_in [1] $end
$var wire 1 G p_in [0] $end
$var reg 1 T s_out $end
$var reg 8 U temp [7:0] $end
$upscope $end

$scope module S1 $end
$var wire 1 1 clk $end
$var wire 1 2 rst $end
$var wire 1 H s_in $end
$var wire 1 7 mode $end
$var reg 8 V p_out [7:0] $end
$var reg 8 W temp [7:0] $end
$upscope $end

$scope module F2 $end
$var wire 1 1 clk $end
$var wire 1 2 rst $end
$var wire 1 5 wr $end
$var wire 1 6 rd $end
$var wire 1 I d_in [7] $end
$var wire 1 J d_in [6] $end
$var wire 1 K d_in [5] $end
$var wire 1 L d_in [4] $end
$var wire 1 M d_in [3] $end
$var wire 1 N d_in [2] $end
$var wire 1 O d_in [1] $end
$var wire 1 P d_in [0] $end
$var reg 8 X d_out [7:0] $end
$var reg 3 Y w_ptr [2:0] $end
$var reg 3 Z r_ptr [2:0] $end
$upscope $end
$upscope $end
$upscope $end
$enddefinitions $end
#0
$dumpvars
0!
0"
0#
0$
0%
0&
1'
b0 (
b0 Q
b0 R
b0 S
0T
b0 U
b0 V
b0 W
b0 X
b0 Y
b0 Z
00
0/
0.
0-
0,
0+
0*
0)
0G
0F
0E
0D
0C
0B
0A
0@
0H
0P
0O
0N
0M
0L
0K
0J
0I
0?
0>
0=
0<
0;
0:
09
08
17
06
05
04
03
02
01
$end
#5000
1!
11
#10000
1"
0!
12
01
#15000
b10010 (
1#
1!
1>
1;
13
11
b1 R
#20000
0!
01
#25000
0#
1$
1!
03
14
11
b10010 Q
b1 S
1F
1C
#30000
0!
01
#35000
0$
0'
1!
04
07
11
#40000
0!
01
#45000
1!
11
#50000
0!
01
#55000
1!
11
#60000
0!
01
#65000
1!
11
#70000
0!
01
#75000
1!
11
#80000
0!
01
#85000
1!
11
#90000
0!
01
#95000
1!
11
#100000
0!
01
#105000
1!
11
#110000
0!
01
#115000
1'
1%
1!
17
15
11
b1 Y
b10010 U
#120000
0!
01
#125000
0%
1&
1!
05
16
11
b1 Z
#130000
0!
01
#135000
0&
1!
06
11
#140000
0!
01
#145000
1!
11
#150000
0!
01
#155000
1!
11
#160000
b101011 (
1#
0!
1?
1<
0;
1:
13
01
#165000
1!
11
b10 R
#170000
0#
1$
0!
03
14
01
#175000
1!
11
b101011 Q
b10 S
1G
1D
0C
1B
#180000
0$
0'
0!
04
07
01
#185000
1!
11
b1001 U
#190000
0!
01
#195000
1!
11
1T
b100 U
1H
#200000
0!
01
#205000
1!
11
b10000000 W
0T
b10 U
0H
#210000
0!
01
#215000
1!
11
b1 U
b1000000 W
#220000
0!
01
#225000
1!
11
b100000 W
1T
b0 U
1H
#230000
0!
01
#235000
1!
11
0T
b10010000 W
0H
#240000
0!
01
#245000
1!
11
b1001000 W
#250000
0!
01
#255000
1!
11
b100100 W
#260000
1'
1%
0!
17
15
01
#265000
1!
11
b10 Y
b101011 U
b100100 V
1N
1K
#270000
0%
1&
0!
05
16
01
#275000
1!
11
b10 Z
#280000
0&
0!
06
01
#285000
1!
11
#290000
b1000000 (
1#
0!
0?
0>
0<
0:
19
13
01
#295000
1!
11
b11 R
#300000
0#
1$
0!
03
14
01
#305000
1!
11
b1000000 Q
b11 S
0G
0F
0D
0B
1A
#310000
0$
0'
0!
04
07
01
#315000
1!
11
b10010 W
1T
b10101 U
1H
#320000
0!
01
#325000
1!
11
b1010 U
b10001001 W
#330000
0!
01
#335000
1!
11
b11000100 W
0T
b101 U
0H
#340000
0!
01
#345000
1!
11
1T
b10 U
b1100010 W
1H
#350000
0!
01
#355000
1!
11
b10110001 W
0T
b1 U
0H
#360000
0!
01
#365000
1!
11
1T
b0 U
b1011000 W
1H
#370000
0!
01
#375000
1!
11
b10101100 W
0T
0H
#380000
0!
01
#385000
1!
11
b1010110 W
#390000
1'
1%
0!
17
15
01
#395000
1!
11
b11 Y
b1000000 U
b1010110 V
1O
1L
0K
1J
#400000
0%
1&
0!
05
16
01
#405000
1!
11
b100100 X
b11 Z
1.
1+
#410000
0&
0!
06
01
#415000
b10010 (
1#
1!
1>
1;
09
13
11
b100 R
#420000
0!
01
#425000
0#
1$
1!
03
14
11
b10010 Q
b100 S
1F
1C
0A
#430000
0!
01
#435000
0$
0'
1!
04
07
11
b101011 W
b100000 U
#440000
0!
01
#445000
1!
11
b10000 U
b10101 W
#450000
0!
01
#455000
1!
11
b1010 W
b1000 U
#460000
0!
01
#465000
1!
11
b100 U
b101 W
#470000
0!
01
#475000
1!
11
b10 W
b10 U
#480000
0!
01
#485000
1!
11
b1 U
b1 W
#490000
0!
01
#495000
1!
11
b0 W
1T
b0 U
1H
#500000
0!
01
#505000
1!
11
0T
b10000000 W
0H
#510000
0!
01
#515000
1'
1%
1!
17
15
11
b100 Y
b10000000 V
b10010 U
0O
0N
0L
0J
1I
#520000
0!
01
#525000
0%
1&
1!
05
16
11
b1010110 X
b100 Z
1/
1,
0+
1*
#530000
0!
01
#535000
0&
1!
06
11
#540000
0!
01
#545000
1!
11
#550000
0!
01
#555000
1!
11
#560000
b101011 (
1#
0!
1?
1<
0;
1:
13
01
#565000
1!
11
b101 R
#570000
0#
1$
0!
03
14
01
#575000
1!
11
b101011 Q
b101 S
1G
1D
0C
1B
#580000
0$
0'
0!
04
07
01
#585000
1!
11
b1000000 W
b1001 U
#590000
0!
01
#595000
1!
11
1T
b100 U
b100000 W
1H
#600000
0!
01
#605000
1!
11
b10010000 W
0T
b10 U
0H
#610000
0!
01
#615000
1!
11
b1 U
b1001000 W
#620000
0!
01
#625000
1!
11
b100100 W
1T
b0 U
1H
#630000
0!
01
#635000
1!
11
0T
b10010010 W
0H
#640000
0!
01
#645000
1!
11
b1001001 W
#650000
0!
01
#655000
1!
11
b100100 W
#660000
1'
1%
0!
17
15
01
#665000
1!
11
b101 Y
b101011 U
b100100 V
1N
1K
0I
#670000
0%
1&
0!
05
16
01
#675000
1!
11
b10000000 X
b101 Z
0/
0.
0,
0*
1)
#680000
0&
0!
06
01
#685000
1!
11
#690000
b1000000 (
1#
0!
0?
0>
0<
0:
19
13
01
#695000
1!
11
b110 R
#700000
0#
1$
0!
03
14
01
#705000
1!
11
b1000000 Q
b110 S
0G
0F
0D
0B
1A
#710000
0$
0'
0!
04
07
01
#715000
1!
11
b10010 W
1T
b10101 U
1H
#720000
0!
01
#725000
1!
11
b1010 U
b10001001 W
#730000
0!
01
#735000
1!
11
b11000100 W
0T
b101 U
0H
#740000
0!
01
#745000
1!
11
1T
b10 U
b1100010 W
1H
#750000
0!
01
#755000
1!
11
b10110001 W
0T
b1 U
0H
#760000
0!
01
#765000
1!
11
1T
b0 U
b1011000 W
1H
#770000
0!
01
#775000
1!
11
b10101100 W
0T
0H
#780000
0!
01
#785000
1!
11
b1010110 W
#790000
1'
1%
0!
17
15
01
#795000
1!
11
b110 Y
b1000000 U
b1010110 V
1O
1L
0K
1J
#800000
0%
1&
0!
05
16
01
#805000
1!
11
b100100 X
b110 Z
1.
1+
0)
#810000
0&
0!
06
01
#815000
b10010 (
1#
1!
1>
1;
09
13
11
b111 R
#820000
0!
01
#825000
0#
1$
1!
03
14
11
b10010 Q
b111 S
1F
1C
0A
#830000
0!
01
#835000
0$
0'
1!
04
07
11
b101011 W
b100000 U
#840000
0!
01
#845000
1!
11
b10000 U
b10101 W
#850000
0!
01
#855000
1!
11
b1010 W
b1000 U
#860000
0!
01
#865000
1!
11
b100 U
b101 W
#870000
0!
01
#875000
1!
11
b10 W
b10 U
#880000
0!
01
#885000
1!
11
b1 U
b1 W
#890000
0!
01
#895000
1!
11
b0 W
1T
b0 U
1H
#900000
0!
01
#905000
1!
11
0T
b10000000 W
0H
#910000
0!
01
#915000
1'
1%
1!
17
15
11
b111 Y
b10000000 V
b10010 U
0O
0N
0L
0J
1I
#920000
0!
01
#925000
0%
1&
1!
05
16
11
b1010110 X
b111 Z
1/
1,
0+
1*
#930000
0!
01
#935000
0&
1!
06
11
#940000
0!
01
#945000
1!
11
#950000
0!
01
#955000
1!
11
#960000
b101011 (
1#
0!
1?
1<
0;
1:
13
01
#965000
1!
11
b0 R
#970000
0